{
  "batiments": {
    "accueil": {
      "label": "Accueil",
      "size": [3, 2],
      "couleur": [0.18, 0.48, 0.82, 0.85],
      "couleur_contour": [0.05, 0.25, 0.55, 1.0],
      "capacite_max": 1
    },
    "tente": {
      "label": "Tente",
      "size": [2, 2],
      "couleur": [0.35, 0.70, 0.35, 0.85],
      "couleur_contour": [0.10, 0.45, 0.10, 1.0],
      "capacite_max": 1
    },
    "caravane": {
      "label": "Caravane",
      "size": [3, 2],
      "couleur": [0.85, 0.75, 0.40, 0.85],
      "couleur_contour": [0.60, 0.45, 0.10, 1.0],
      "capacite_max": 1
    },
    "mobil-home": {
      "label": "Mobil-Home",
      "size": [3, 3],
      "couleur": [0.35, 0.55, 0.75, 0.85],
      "couleur_contour": [0.10, 0.30, 0.55, 1.0],
      "capacite_max": 1
    },
    "sanitaires": {
      "label": "Sanitaires",
      "size": [2, 3],
      "couleur": [0.78, 0.90, 0.96, 0.85],
      "couleur_contour": [0.20, 0.50, 0.72, 1.0],
      "capacite_max": 4
    },
    "snack": {
      "label": "Snack",
      "size": [3, 3],
      "couleur": [0.96, 0.80, 0.20, 0.85],
      "couleur_contour": [0.72, 0.45, 0.05, 1.0],
      "capacite_max": 12
    },
    "piscine": {
      "label": "Piscine",
      "size": [5, 4],
      "couleur": [0.55, 0.55, 0.55, 0.85],
      "couleur_contour": [0.2, 0.2, 0.2, 1.0],
      "capacite_max": 10
    },
    "chemin": {
      "label": "Chemin",
      "size": [1, 1],
      "couleur": [0.55, 0.55, 0.55, 0.85],
      "couleur_contour": [0.2, 0.2, 0.2, 1.0],
      "capacite_max": 0
    }
  }
}
